bleu_torch/__init__.py
bleu_torch/bleu_torch.py
bleu_torch-1.0.0.dist-info/licenses/LICENSE
bleu_torch-1.0.0.dist-info/METADATA
bleu_torch-1.0.0.dist-info/WHEEL
bleu_torch-1.0.0.dist-info/top_level.txt
bleu_torch-1.0.0.dist-info/RECORD
