Metadata-Version: 2.4
Name: bleu-torch
Version: 1.0.0
Summary: PyTorch module for differentiable BLEU score computation that supports end-to-end training
Home-page: https://github.com/Ghost---Shadow/bleu-torch
Author: bleu-torch contributors
License: MIT
Project-URL: Homepage, https://github.com/your-username/bleu-torch
Project-URL: Documentation, https://github.com/your-username/bleu-torch#readme
Project-URL: Repository, https://github.com/your-username/bleu-torch.git
Project-URL: Issues, https://github.com/your-username/bleu-torch/issues
Keywords: bleu,pytorch,nlp,differentiable,neural-machine-translation,evaluation,training
Classifier: Development Status :: 5 - Production/Stable
Classifier: Intended Audience :: Developers
Classifier: Intended Audience :: Science/Research
Classifier: License :: OSI Approved :: MIT License
Classifier: Operating System :: OS Independent
Classifier: Programming Language :: Python :: 3
Classifier: Programming Language :: Python :: 3.8
Classifier: Programming Language :: Python :: 3.9
Classifier: Programming Language :: Python :: 3.10
Classifier: Programming Language :: Python :: 3.11
Classifier: Programming Language :: Python :: 3.12
Classifier: Topic :: Scientific/Engineering :: Artificial Intelligence
Classifier: Topic :: Software Development :: Libraries :: Python Modules
Classifier: Topic :: Text Processing :: Linguistic
Requires-Python: >=3.8
License-File: LICENSE
Requires-Dist: torch>=1.9.0
Requires-Dist: numpy>=1.19.0
Provides-Extra: dev
Requires-Dist: pytest>=6.0; extra == "dev"
Requires-Dist: matplotlib>=3.3.0; extra == "dev"
Requires-Dist: black; extra == "dev"
Requires-Dist: isort; extra == "dev"
Requires-Dist: flake8; extra == "dev"
Provides-Extra: test
Requires-Dist: pytest>=6.0; extra == "test"
Requires-Dist: matplotlib>=3.3.0; extra == "test"
Dynamic: home-page
Dynamic: license-file
Dynamic: requires-python
